fastapi_openid_google/__init__.py
fastapi_openid_google-0.0.0.dist-info/LICENSE
fastapi_openid_google-0.0.0.dist-info/METADATA
fastapi_openid_google-0.0.0.dist-info/WHEEL
fastapi_openid_google-0.0.0.dist-info/top_level.txt
fastapi_openid_google-0.0.0.dist-info/RECORD
