Metadata-Version: 2.1
Name: fastapi_openid_google
Version: 0.0.0
Summary: Google OpenID integration for FastAPI
Home-page: https://github.com/svaponi/fastapi_openid_google
Author: svaponi
Classifier: Development Status :: 4 - Beta
Classifier: Programming Language :: Python :: 3
Classifier: License :: OSI Approved :: MIT License
Classifier: Operating System :: OS Independent
Requires-Python: >=3.11
License-File: LICENSE
Requires-Dist: fastapi-openid-google
Requires-Dist: oauthlib
Requires-Dist: requests
Provides-Extra: local
Requires-Dist: uvicorn ; extra == 'local'
Requires-Dist: python-dotenv ; extra == 'local'
